{
    "allowRemoteResourceManagement": false,
    "policyEnforcementMode": "ENFORCING",
    "resources": [
        {
            "name": "PRAKTIKUMSPLANER_BACKEND_READ_THEENTITY",
            "type": "aa-a-praktikumsplaner-backend-service",
            "scopes": []
        },
        {
            "name": "PRAKTIKUMSPLANER_BACKEND_WRITE_THEENTITY",
            "type": "aa-a-praktikumsplaner-backend-service",
            "scopes": []
        },
        {
            "name": "PRAKTIKUMSPLANER_BACKEND_DELETE_THEENTITY",
            "type": "aa-a-praktikumsplaner-backend-service",
            "scopes": []
        }
    ],
    "policies": [
        {
            "name": "rolepolicy_admin",
            "type": "role",
            "logic": "POSITIVE",
            "decisionStrategy": "AFFIRMATIVE",
            "config": {
                "roles": "[{\"id\":\"aa-a/clientrole_admin\",\"required\":false}]"
            }
        },
        {
            "name": "rolepolicy_readonly",
            "type": "role",
            "logic": "POSITIVE",
            "decisionStrategy": "AFFIRMATIVE",
            "config": {
                "roles": "[{\"id\":\"aa-a/clientrole_readonly\",\"required\":false}]"
            }
        },
        {
            "name": "permission_PRAKTIKUMSPLANER_BACKEND_DELETE_THEENTITY",
            "type": "resource",
            "logic": "POSITIVE",
            "decisionStrategy": "AFFIRMATIVE",
            "config": {
                "resources": "[\"PRAKTIKUMSPLANER_BACKEND_DELETE_THEENTITY\"]",
                "applyPolicies": "[\"rolepolicy_admin\"]"
            }
        },
        {
            "name": "permission_PRAKTIKUMSPLANER_BACKEND_WRITE_THEENTITY",
            "type": "resource",
            "logic": "POSITIVE",
            "decisionStrategy": "AFFIRMATIVE",
            "config": {
                "resources": "[\"PRAKTIKUMSPLANER_BACKEND_WRITE_THEENTITY\"]",
                "applyPolicies": "[\"rolepolicy_admin\"]"
            }
        },
        {
            "name": "permission_PRAKTIKUMSPLANER_BACKEND_READ_THEENTITY",
            "type": "resource",
            "logic": "POSITIVE",
            "decisionStrategy": "AFFIRMATIVE",
            "config": {
                "resources": "[\"PRAKTIKUMSPLANER_BACKEND_READ_THEENTITY\"]",
                "applyPolicies": "[\"rolepolicy_admin\",\"rolepolicy_readonly\"]"
            }
        }
    ],
    "scopes": []
}
